pygreatcircledistance.py
pygreatcircledistance-0.1.0.dist-info/WHEEL
pygreatcircledistance-0.1.0.dist-info/METADATA
pygreatcircledistance-0.1.0.dist-info/RECORD
