Metadata-Version: 2.1
Name: pygreatcircledistance
Version: 0.1.0
Summary: Calculate the distance between two GPS coordinates in meters
Home-page: https://github.com/shpaker/pyGreatCircleDistance
Author: Aleksandr Shpak
Author-email: shpaker@gmail.com
Requires-Python: >=3.7.2,<4.0.0
Classifier: Programming Language :: Python :: 3
Classifier: Programming Language :: Python :: 3.8
Classifier: Programming Language :: Python :: 3.9
Classifier: Programming Language :: Python :: 3.10
Classifier: Programming Language :: Python :: 3.11
Project-URL: Repository, https://github.com/shpaker/pyGreatCircleDistance
